mongo2neo4j/__init__.py
mongo2neo4j/__main__.py
mongo2neo4j/py.typed
mongo2neo4j-1.0.4.dist-info/LICENSE
mongo2neo4j-1.0.4.dist-info/METADATA
mongo2neo4j-1.0.4.dist-info/WHEEL
mongo2neo4j-1.0.4.dist-info/entry_points.txt
mongo2neo4j-1.0.4.dist-info/top_level.txt
mongo2neo4j-1.0.4.dist-info/RECORD
