Metadata-Version: 2.1
Name: mongo2neo4j
Version: 1.0.4
Summary: Imports object structures generated by MongoDB object relation mappers (like Mongoose) into Neo4j for exploration with SemSpect
Author: Marko Luther, Paul Holleis, Thorsten Liebig, Vincent Vialard
License: GNU GENERAL PUBLIC LICENSE
Project-URL: Homepage, https://makomo.github.io/mongo2neo4j/
Project-URL: Issue Tracker, https://github.com/MAKOMO/mongo2neo4j/issues
Keywords: MongoDB,Neo4j,Mongoose,SemSpect,exploration,conversion
Classifier: Programming Language :: Python :: 3 :: Only
Classifier: License :: OSI Approved :: GNU General Public License v3 (GPLv3)
Classifier: Operating System :: OS Independent
Classifier: Topic :: Other/Nonlisted Topic
Requires-Python: >=3.11
License-File: LICENSE
Requires-Dist: pymongo >=4.10.1
Requires-Dist: neo4j >=5.25.0
Provides-Extra: dev
Requires-Dist: mypy >=1.13.0 ; extra == 'dev'
Requires-Dist: pyright >=1.1.386 ; extra == 'dev'
Requires-Dist: ruff >=0.7.1 ; extra == 'dev'
Requires-Dist: pylint >=3.3.1 ; extra == 'dev'
Requires-Dist: pytest >=8.3.3 ; extra == 'dev'
Requires-Dist: pytest-cov >=5.0.0 ; extra == 'dev'
Requires-Dist: coverage-badge >=1.1.2 ; extra == 'dev'
Requires-Dist: pre-commit >=4.0.1 ; extra == 'dev'
Requires-Dist: twine >=5.1.1 ; extra == 'dev'
Requires-Dist: build >=1.2.2.post1 ; extra == 'dev'
Requires-Dist: codespell >=2.3.0 ; extra == 'dev'
